silver_payu/__init__.py
silver_payu/errors.py
silver_payu/forms.py
silver_payu/payment_processors.py
silver_payu/urls.py
silver_payu/views.py
silver_payu/migrations/0001_initial.py
silver_payu/migrations/__init__.py
silver_payu/models/__init__.py
silver_payu/models/payment_methods.py
silver_payu/templates/forms/payu_manual/transaction_form.html
silver_payu/templates/forms/payu_triggered/transaction_form.html
silver_payu/templates/payu/3ds_form.html
silver_payu/templates/payu/get_billing_details_form.html
silver_payu/templates/payu/payu_lu_form.html
silver_payu/templates/payu/transaction_form.html
tests/__init__.py
tests/conftest.py
tests/factories.py
tests/fixtures.py
tests/test_forms.py
tests/test_models.py
silver_payu-0.7.0.dist-info/LICENSE
silver_payu-0.7.0.dist-info/METADATA
silver_payu-0.7.0.dist-info/WHEEL
silver_payu-0.7.0.dist-info/top_level.txt
silver_payu-0.7.0.dist-info/RECORD
