Metadata-Version: 2.1
Name: silver-payu
Version: 0.7.0
Home-page: https://github.com/silverapp/silver-payu
Author: Presslabs
Author-email: ping@presslabs.com
License: Apache 2.0
Keywords: django,app,reusable,billing,invoicing,api
Platform: OS Independent
Classifier: Environment :: Web Environment
Classifier: Framework :: Django :: 3.1
Classifier: Framework :: Django :: 3.2
Classifier: Development Status :: 5 - Production/Stable
Classifier: License :: OSI Approved :: Apache Software License
Classifier: Programming Language :: Python :: 3.7
License-File: LICENSE
Requires-Dist: django-payu-ro (>=1.4.1)
Requires-Dist: django-ipware (>=3.0.2)
